gitignore_gen/__init__.py
gitignore_gen/cli.py
gitignore_gen/main.py
gitignore_gen/caching/__init__.py
gitignore_gen/caching/core.py
gitignore_gen/template_management/__init__.py
gitignore_gen/template_management/base.py
gitignore_gen-0.1.1.dist-info/LICENSE
gitignore_gen-0.1.1.dist-info/METADATA
gitignore_gen-0.1.1.dist-info/WHEEL
gitignore_gen-0.1.1.dist-info/entry_points.txt
gitignore_gen-0.1.1.dist-info/top_level.txt
gitignore_gen-0.1.1.dist-info/RECORD
