Metadata-Version: 2.2
Name: gitignore-gen
Version: 0.1.1
Summary: A tool to generate .gitignore files for various languages and frameworks
Author: Naymul Islam
Author-email: Naymul Islam <naymul504@gmail.com>
Project-URL: Homepage, https://github.com/ai-naymul/gitignore-gen
Project-URL: Issues, https://github.com/ai-naymul/gitignore-gen/issues
Classifier: Programming Language :: Python :: 3
Classifier: Operating System :: OS Independent
Classifier: License :: OSI Approved :: MIT License
Requires-Python: >=3.6
License-File: LICENSE
Dynamic: author
Dynamic: requires-python
